odoo/addons/account_invoice_download_scaleway/README.rst
odoo/addons/account_invoice_download_scaleway/__init__.py
odoo/addons/account_invoice_download_scaleway/__manifest__.py
odoo/addons/account_invoice_download_scaleway/demo/scaleway.xml
odoo/addons/account_invoice_download_scaleway/i18n/account_invoice_download_scaleway.pot
odoo/addons/account_invoice_download_scaleway/i18n/es.po
odoo/addons/account_invoice_download_scaleway/i18n/it.po
odoo/addons/account_invoice_download_scaleway/models/__init__.py
odoo/addons/account_invoice_download_scaleway/models/account_invoice_download_config.py
odoo/addons/account_invoice_download_scaleway/readme/CONFIGURE.md
odoo/addons/account_invoice_download_scaleway/readme/CONTRIBUTORS.md
odoo/addons/account_invoice_download_scaleway/readme/DESCRIPTION.md
odoo/addons/account_invoice_download_scaleway/readme/USAGE.md
odoo/addons/account_invoice_download_scaleway/static/description/icon.png
odoo/addons/account_invoice_download_scaleway/static/description/index.html
odoo/addons/account_invoice_download_scaleway/views/account_invoice_download_config.xml
odoo_addon_account_invoice_download_scaleway-18.0.1.0.0.3.dist-info/METADATA
odoo_addon_account_invoice_download_scaleway-18.0.1.0.0.3.dist-info/WHEEL
odoo_addon_account_invoice_download_scaleway-18.0.1.0.0.3.dist-info/top_level.txt
odoo_addon_account_invoice_download_scaleway-18.0.1.0.0.3.dist-info/RECORD
